somecomfort_homie/__init__.py
somecomfort_homie/sch.py
somecomfort_homie/somecomfort_homie.py
somecomfort_homie/homie_device/__init__.py
somecomfort_homie/homie_device/device_honeywell_thermostat.py
somecomfort_homie/homie_device/device_total_comfort_account.py
Somecomfort_Homie_4-0.3.6.dist-info/LICENSE
Somecomfort_Homie_4-0.3.6.dist-info/METADATA
Somecomfort_Homie_4-0.3.6.dist-info/WHEEL
Somecomfort_Homie_4-0.3.6.dist-info/top_level.txt
Somecomfort_Homie_4-0.3.6.dist-info/RECORD
