Metadata-Version: 2.1
Name: Somecomfort-Homie-4
Version: 0.3.6
Summary: Homie 4 for Honeywell Total Comfort North America
Home-page: https://github.com/mjcumming/Somecomfort-Homie
Author: Michael Cumming
Author-email: mike@4831.com
License: UNKNOWN
Keywords: HOMIE,MQTT,Somecomfort,Honeywell
Platform: UNKNOWN
Classifier: Programming Language :: Python :: 3
Classifier: License :: OSI Approved :: MIT License
Classifier: Operating System :: OS Independent
Requires-Python: >=3.5.*
License-File: LICENSE
Requires-Dist: Homie4 (>=0.2.7)
Requires-Dist: somecomfort
Requires-Dist: pyyaml
Requires-Dist: timer3
